{"items": [{"company_id": "6b5bdd133e7b96d2", "domain": "www.theentrepreneurlawyers.com", "website_url": "https://www.theentrepreneurlawyers.com/", "website": "https://www.theentrepreneurlawyers.com/", "phone_raw": null, "address": null, "category": null, "rating": null, "source_tags": ["gmaps_direct"], "gmaps_url": "https://www.google.com/maps/place/The+Entrepreneur+Lawyers/data=!4m7!3m6!1s0x88d9a7a16bb00001:0x34b564285cf2edcd!8m2!3d26.1235643!4d-80.141201!16s%2Fg%2F11f63ybwym!19sChIJAQCwa6Gn2YgRze3yXChktTQ?authuser=0&hl=en&rclk=1", "company_name": "The Entrepreneur Lawyers", "phone_e164": null, "phone_valid": null, "phone_type": null, "phones_found": ["1-833-529-8357", "1(833)529-8357", "1833-529-8357"], "social_links": {"linkedin": ["https://www.linkedin.com/company/theentrepreneurlawyers/"], "twitter": [], "instagram": ["https://www.instagram.com/the_entrepreneur_lawyers"], "facebook": ["https://www.facebook.com/TheEntrepreneurLawyers"], "youtube": [], "tiktok": []}, "emails_found": [{"email": "hello@www.theentrepreneurlawyers.com", "source": "hunter", "validation": {"email": "hello@www.theentrepreneurlawyers.com", "is_valid": false, "score": 0.0, "reason": "no_mx"}}], "primary_email": "hello@www.theentrepreneurlawyers.com", "waterfall_verified": true, "enrichment_industry": "Software", "enrichment_employee_count": 50, "enrichment_linkedin_url": "https://www.linkedin.com/company/www", "description": "Www.theentrepreneurlawyers.com is a leading provider of innovative solutions in the software industry, currently expanding their team.", "linkedin_contacts": [{"full_name": "Alex Founder", "title": "Founder & CEO", "company": "The Entrepreneur Lawyers"}, {"full_name": "Mia Head of Growth", "title": "Head of Growth", "company": "The Entrepreneur Lawyers"}], "intent_signals": [], "ai_outreach_line": "I came across The Entrepreneur Lawyers and was impressed by your presence in the Software.", "lead_score": 80, "relevance_score": 0.0}], "total": 1}